{
  "manifestVersion": "3.2",
  "admin": {
    "address": "0x5FC8d32690cc91D4c39d9d3abcBD16989F875707",
    "txHash": "0x0c75b510cb2af216f75aab3a0a9e3f8f3565f06eb65593d93ede82e0df7e1261"
  },
  "proxies": [
    {
      "address": "0x0E801D84Fa97b50751Dbf25036d067dCf18858bF",
      "txHash": "0x138cd952ff19d7d3abdfb6fec511faf29c84cb67df21c256760f0b9e3a5c0a8f",
      "kind": "transparent"
    },
    {
      "address": "0x5FC8d32690cc91D4c39d9d3abcBD16989F875707",
      "txHash": "0x320d54c5007adba60d377f8e9a33afda0546641d5019e2197338c5d93665dec5",
      "kind": "transparent"
    },
    {
      "address": "0x0165878A594ca255338adfa4d48449f69242Eb8F",
      "txHash": "0x6db28f745f6aebf4e27d74cf050865afd5c17127bfa8e1b7adb3436d7a20e0e8",
      "kind": "transparent"
    },
    {
      "address": "0x9d4454B023096f34B160D6B654540c56A1F81688",
      "txHash": "0xa5f608b717c014116d028153194280ab95ca312e2e407e6b0fa9e02dbd0d62c1",
      "kind": "transparent"
    }
  ],
  "impls": {
    "9eca9c569c3f0c8c7a151494f220c3a1a5372fdc100ec4673b7edf334cdbf0c9": {
      "address": "0xDc64a140Aa3E981100a9becA4E685f962f0cF6C9",
      "txHash": "0xdf9a90cc40419a99e15c2272dbd9dc843913b329a037ae4c05323030fb5c530a",
      "layout": {
        "storage": [
          {
            "label": "_initialized",
            "offset": 0,
            "slot": "0",
            "type": "t_bool",
            "contract": "Initializable",
            "src": "@openzeppelin/contracts-upgradeable/proxy/utils/Initializable.sol:39"
          },
          {
            "label": "_initializing",
            "offset": 1,
            "slot": "0",
            "type": "t_bool",
            "contract": "Initializable",
            "src": "@openzeppelin/contracts-upgradeable/proxy/utils/Initializable.sol:44"
          },
          {
            "label": "__gap",
            "offset": 0,
            "slot": "1",
            "type": "t_array(t_uint256)50_storage",
            "contract": "ContextUpgradeable",
            "src": "@openzeppelin/contracts-upgradeable/utils/ContextUpgradeable.sol:36"
          },
          {
            "label": "_owner",
            "offset": 0,
            "slot": "51",
            "type": "t_address",
            "contract": "OwnableUpgradeable",
            "src": "@openzeppelin/contracts-upgradeable/access/OwnableUpgradeable.sol:22"
          },
          {
            "label": "__gap",
            "offset": 0,
            "slot": "52",
            "type": "t_array(t_uint256)49_storage",
            "contract": "OwnableUpgradeable",
            "src": "@openzeppelin/contracts-upgradeable/access/OwnableUpgradeable.sol:87"
          },
          {
            "label": "_HASHED_NAME",
            "offset": 0,
            "slot": "101",
            "type": "t_bytes32",
            "contract": "EIP712Upgradeable",
            "src": "@openzeppelin/contracts-upgradeable/utils/cryptography/draft-EIP712Upgradeable.sol:30"
          },
          {
            "label": "_HASHED_VERSION",
            "offset": 0,
            "slot": "102",
            "type": "t_bytes32",
            "contract": "EIP712Upgradeable",
            "src": "@openzeppelin/contracts-upgradeable/utils/cryptography/draft-EIP712Upgradeable.sol:31"
          },
          {
            "label": "__gap",
            "offset": 0,
            "slot": "103",
            "type": "t_array(t_uint256)50_storage",
            "contract": "EIP712Upgradeable",
            "src": "@openzeppelin/contracts-upgradeable/utils/cryptography/draft-EIP712Upgradeable.sol:118"
          },
          {
            "label": "timelock",
            "offset": 0,
            "slot": "153",
            "type": "t_contract(ITimelock)8499",
            "contract": "GovernorCharlie",
            "src": "src/contracts/governance/GovernorCharlie.sol:80"
          },
          {
            "label": "shibui",
            "offset": 0,
            "slot": "154",
            "type": "t_contract(IShibui)9326",
            "contract": "GovernorCharlie",
            "src": "src/contracts/governance/GovernorCharlie.sol:82"
          },
          {
            "label": "votingPeriod",
            "offset": 0,
            "slot": "155",
            "type": "t_uint256",
            "contract": "GovernorCharlie",
            "src": "src/contracts/governance/GovernorCharlie.sol:89"
          },
          {
            "label": "votingDelay",
            "offset": 0,
            "slot": "156",
            "type": "t_uint256",
            "contract": "GovernorCharlie",
            "src": "src/contracts/governance/GovernorCharlie.sol:92"
          },
          {
            "label": "proposalThreshold",
            "offset": 0,
            "slot": "157",
            "type": "t_uint256",
            "contract": "GovernorCharlie",
            "src": "src/contracts/governance/GovernorCharlie.sol:95"
          },
          {
            "label": "initialProposalId",
            "offset": 0,
            "slot": "158",
            "type": "t_uint256",
            "contract": "GovernorCharlie",
            "src": "src/contracts/governance/GovernorCharlie.sol:98"
          },
          {
            "label": "proposalCount",
            "offset": 0,
            "slot": "159",
            "type": "t_uint256",
            "contract": "GovernorCharlie",
            "src": "src/contracts/governance/GovernorCharlie.sol:105"
          },
          {
            "label": "proposals",
            "offset": 0,
            "slot": "160",
            "type": "t_mapping(t_uint256,t_struct(Proposal)8343_storage)",
            "contract": "GovernorCharlie",
            "src": "src/contracts/governance/GovernorCharlie.sol:108"
          },
          {
            "label": "latestProposalIds",
            "offset": 0,
            "slot": "161",
            "type": "t_mapping(t_address,t_uint256)",
            "contract": "GovernorCharlie",
            "src": "src/contracts/governance/GovernorCharlie.sol:111"
          },
          {
            "label": "allowlistGuardian",
            "offset": 0,
            "slot": "162",
            "type": "t_address",
            "contract": "GovernorCharlie",
            "src": "src/contracts/governance/GovernorCharlie.sol:118"
          },
          {
            "label": "allowlistAccountExpirations",
            "offset": 0,
            "slot": "163",
            "type": "t_mapping(t_address,t_uint256)",
            "contract": "GovernorCharlie",
            "src": "src/contracts/governance/GovernorCharlie.sol:121"
          }
        ],
        "types": {
          "t_address": {
            "label": "address"
          },
          "t_array(t_address)dyn_storage": {
            "label": "address[]"
          },
          "t_array(t_bytes_storage)dyn_storage": {
            "label": "bytes[]"
          },
          "t_array(t_string_storage)dyn_storage": {
            "label": "string[]"
          },
          "t_array(t_uint256)49_storage": {
            "label": "uint256[49]"
          },
          "t_array(t_uint256)50_storage": {
            "label": "uint256[50]"
          },
          "t_array(t_uint256)dyn_storage": {
            "label": "uint256[]"
          },
          "t_bool": {
            "label": "bool"
          },
          "t_bytes32": {
            "label": "bytes32"
          },
          "t_bytes_storage": {
            "label": "bytes"
          },
          "t_contract(IShibui)9326": {
            "label": "contract IShibui"
          },
          "t_contract(ITimelock)8499": {
            "label": "contract ITimelock"
          },
          "t_mapping(t_address,t_struct(Receipt)8287_storage)": {
            "label": "mapping(address => struct IGovernorCharlie.Receipt)"
          },
          "t_mapping(t_address,t_uint256)": {
            "label": "mapping(address => uint256)"
          },
          "t_mapping(t_uint256,t_struct(Proposal)8343_storage)": {
            "label": "mapping(uint256 => struct IGovernorCharlie.Proposal)"
          },
          "t_string_storage": {
            "label": "string"
          },
          "t_struct(Proposal)8343_storage": {
            "label": "struct IGovernorCharlie.Proposal",
            "members": [
              {
                "label": "id",
                "type": "t_uint256"
              },
              {
                "label": "proposer",
                "type": "t_address"
              },
              {
                "label": "eta",
                "type": "t_uint256"
              },
              {
                "label": "targets",
                "type": "t_array(t_address)dyn_storage"
              },
              {
                "label": "values",
                "type": "t_array(t_uint256)dyn_storage"
              },
              {
                "label": "signatures",
                "type": "t_array(t_string_storage)dyn_storage"
              },
              {
                "label": "calldatas",
                "type": "t_array(t_bytes_storage)dyn_storage"
              },
              {
                "label": "timestamp",
                "type": "t_uint256"
              },
              {
                "label": "startBlock",
                "type": "t_uint256"
              },
              {
                "label": "endTimestamp",
                "type": "t_uint256"
              },
              {
                "label": "forVotes",
                "type": "t_uint256"
              },
              {
                "label": "againstVotes",
                "type": "t_uint256"
              },
              {
                "label": "abstainVotes",
                "type": "t_uint256"
              },
              {
                "label": "canceled",
                "type": "t_bool"
              },
              {
                "label": "executed",
                "type": "t_bool"
              },
              {
                "label": "receipts",
                "type": "t_mapping(t_address,t_struct(Receipt)8287_storage)"
              }
            ]
          },
          "t_struct(Receipt)8287_storage": {
            "label": "struct IGovernorCharlie.Receipt",
            "members": [
              {
                "label": "hasVoted",
                "type": "t_bool"
              },
              {
                "label": "support",
                "type": "t_uint8"
              },
              {
                "label": "votes",
                "type": "t_uint96"
              }
            ]
          },
          "t_uint256": {
            "label": "uint256"
          },
          "t_uint8": {
            "label": "uint8"
          },
          "t_uint96": {
            "label": "uint96"
          }
        }
      }
    }
  }
}
